{
  "utcDate": "2026-02-28",
  "answer": "elm",
  "models": [
    {
      "modelId": "model_1",
      "displayName": "Model 1",
      "rankedWords": [
        "elm",
        "pinecone",
        "rainstorm",
        "varnish",
        "anchor",
        "rhythm",
        "harbor",
        "summit",
        "meadow",
        "lantern",
        "drift",
        "willow",
        "whisper",
        "solder",
        "marble",
        "oasis",
        "ripple",
        "granite",
        "canyon",
        "echo",
        "garden",
        "ivory"
      ]
    },
    {
      "modelId": "model_2",
      "displayName": "Model 2",
      "rankedWords": [
        "elm",
        "rainstorm",
        "orbit",
        "harbor",
        "prism",
        "lantern",
        "breeze",
        "whisper",
        "beacon",
        "oasis",
        "cedar",
        "canyon",
        "fable",
        "ivory",
        "lagoon",
        "opal",
        "raven",
        "upland",
        "atlas",
        "daisy",
        "glacier"
      ]
    },
    {
      "modelId": "model_3",
      "displayName": "Model 3",
      "rankedWords": [
        "elm",
        "pinecone",
        "rhythm",
        "summit",
        "lantern",
        "willow",
        "solder",
        "oasis",
        "granite",
        "echo",
        "ivory",
        "monsoon",
        "quartz",
        "upland",
        "coral",
        "glacier",
        "olive",
        "spruce",
        "walnut",
        "blush",
        "feather"
      ]
    }
  ]
}
